{
  "firstName": "Breanna",
  "lastName": "Rippin",
  "street": "8338 N Court Street",
  "city": "Hilllborough",
  "state": "Nevada",
  "zipCode": "27114",
  "phoneNumber": "506.849.0275 x294",
  "ssn": "837948188",
  "username": "Jana.Romaguera19",
  "password": "lEDS_IuyX2VWAXJ",
  "email": "Josianne41@yahoo.com",
  "day": 6,
  "month": "May",
  "year": "2014",
  "company": "Kerluke, Jacobs and Buckridge",
  "address": "Apt. 257",
  "address2": "Apt. 576",
  "country": "India",
  "fullName": "Personal Loan Account",
  "cardNumber": "53558259",
  "cvc": 950,
  "exmonth": 10,
  "exyear": 2034
}